libtc/__init__.py
libtc/__main__.py
libtc/baseclient.py
libtc/bencode.py
libtc/exceptions.py
libtc/liltorrent.py
libtc/management.py
libtc/parse_clients.py
libtc/scgitransport.py
libtc/torrent.py
libtc/utils.py
libtc/clients/__init__.py
libtc/clients/deluge.py
libtc/clients/fakeclient.py
libtc/clients/liltorrent.py
libtc/clients/qbittorrent.py
libtc/clients/rtorrent.py
libtc/clients/transmission.py
libtc/clients/tests/__init__.py
libtc/clients/tests/basetest.py
libtc/clients/tests/test_deluge.py
libtc/clients/tests/test_liltorrent.py
libtc/clients/tests/test_management.py
libtc/clients/tests/test_qbittorrent.py
libtc/clients/tests/test_rtorrent.py
libtc/clients/tests/test_transmission.py
libtc/clients/tests/utils_testclient.py
libtc/tests/__init__.py
libtc/tests/test_liltorrent.py
libtc-1.3.4.dist-info/LICENSE
libtc-1.3.4.dist-info/METADATA
libtc-1.3.4.dist-info/WHEEL
libtc-1.3.4.dist-info/entry_points.txt
libtc-1.3.4.dist-info/top_level.txt
libtc-1.3.4.dist-info/RECORD
