Metadata-Version: 2.1
Name: libtc
Version: 1.3.4
Summary: Bittorrent client library
Home-page: https://github.com/JohnDoee/libtc
Author: Anders Jensen
Author-email: andersandjensen@gmail.com
License: MIT
Platform: UNKNOWN
Classifier: Development Status :: 4 - Beta
Classifier: Intended Audience :: Developers
Classifier: License :: OSI Approved :: MIT License
Classifier: Operating System :: OS Independent
Classifier: Programming Language :: Python
Classifier: Programming Language :: Python :: 3.6
Classifier: Programming Language :: Python :: 3.7
Classifier: Programming Language :: Python :: 3.8
Classifier: Programming Language :: Python :: 3.9
Classifier: Programming Language :: Python :: 3.10
License-File: LICENSE
Requires-Dist: deluge-client (~=1.9.0)
Requires-Dist: pytz
Requires-Dist: requests
Requires-Dist: click (<9.0,>=8.0)
Requires-Dist: tabulate (~=0.8.7)
Requires-Dist: publicsuffixlist (~=0.7.3)
Provides-Extra: liltorrent
Requires-Dist: Flask (~=1.1.2) ; extra == 'liltorrent'
Requires-Dist: waitress (~=1.4.3) ; extra == 'liltorrent'
